libpaste/__init__.py
libpaste/conf.py
libpaste/context_processors.py
libpaste/enums.py
libpaste/forms.py
libpaste/highlight.py
libpaste/models.py
libpaste/urls.py
libpaste/views.py
libpaste/management/__init__.py
libpaste/management/commands/__init__.py
libpaste/management/commands/cleanup_snippets.py
libpaste/migrations/0001_initial.py
libpaste/migrations/0002_upgrade_mptt_fields.py
libpaste/migrations/__init__.py
libpaste/templates/libpaste/base.html
libpaste/templates/libpaste/snippet_details.html
libpaste/templates/libpaste/snippet_details_raw.html
libpaste/templates/libpaste/snippet_diff.html
libpaste/templates/libpaste/snippet_form.html
libpaste/templates/libpaste/snippet_list.html
libpaste/templates/libpaste/snippet_new.html
libpaste/templates/libpaste/snippet_pre.html
libpaste/templates/libpaste/snippet_upload.html
libpaste/templatetags/__init__.py
libpaste/templatetags/libpaste_tags.py
xelpaste/__init__.py
xelpaste/settings.py
xelpaste/urls.py
xelpaste/views.py
xelpaste/wsgi.py
xelpaste/assets/staticfiles.json
xelpaste/assets/mptt/arrow-move-black.d657cbe13d79.png
xelpaste/assets/mptt/arrow-move-black.png
xelpaste/assets/mptt/arrow-move-white.012ecec6e780.png
xelpaste/assets/mptt/arrow-move-white.png
xelpaste/assets/mptt/disclosure-down-black.d5001c451bec.png
xelpaste/assets/mptt/disclosure-down-black.png
xelpaste/assets/mptt/disclosure-down-white.ec4c7552c913.png
xelpaste/assets/mptt/disclosure-down-white.png
xelpaste/assets/mptt/disclosure-right-black.a60e64d77eff.png
xelpaste/assets/mptt/disclosure-right-black.png
xelpaste/assets/mptt/disclosure-right-white.d6493f18627d.png
xelpaste/assets/mptt/disclosure-right-white.png
xelpaste/assets/mptt/draggable-admin.000e549a1ba8.js
xelpaste/assets/mptt/draggable-admin.c2fe4244e1d8.css
xelpaste/assets/mptt/draggable-admin.css
xelpaste/assets/mptt/draggable-admin.js
xelpaste/assets/xelpaste/css/bootstrap.css
xelpaste/assets/xelpaste/css/bootstrap.css.c7ffd8c7a285.map
xelpaste/assets/xelpaste/css/bootstrap.css.map
xelpaste-3.3.3.dist-info/LICENSE
xelpaste-3.3.3.dist-info/METADATA
xelpaste-3.3.3.dist-info/WHEEL
xelpaste-3.3.3.dist-info/top_level.txt
xelpaste-3.3.3.dist-info/RECORD
