Metadata-Version: 2.1
Name: xelpaste
Version: 3.3.3
Summary: Standalone, django-based pastebin with image support.
Home-page: https://github.com/rbarrois/xelpaste/
Author: Martin Mahner
Author-email: raphael.barrois+xelpaste@polytechnique.org
Maintainer: Raphaël Barrois
Maintainer-email: raphael.barrois+xelpaste@polytechnique.org
License: MIT
Keywords: xelpaste,dpaste,pastebin
Classifier: Development Status :: 5 - Production/Stable
Classifier: Environment :: Web Environment
Classifier: Framework :: Django
Classifier: Intended Audience :: Developers
Classifier: License :: OSI Approved :: MIT License
Classifier: Operating System :: OS Independent
Classifier: Programming Language :: Python
Classifier: Programming Language :: Python :: 3
Classifier: Programming Language :: Python :: 3.8
Classifier: Programming Language :: Python :: 3.9
Classifier: Programming Language :: Python :: 3.10
License-File: LICENSE
Requires-Dist: Django (<5.0,>=4.0)
Requires-Dist: django-mptt (>=0.9.1)
Requires-Dist: pygments (>=2.2.0)
Requires-Dist: django-appconf (>=1.0.1)
Requires-Dist: django-sendfile2 (>=0.7.0)
Requires-Dist: getconf (<2,>=1.3.0)
